ctrl_z/__init__.py
ctrl_z/_cli.py
ctrl_z/backup.py
ctrl_z/config.default.yml
ctrl_z/config.py
ctrl_z/db_restore.py
ctrl_z/retention.py
ctrl_z-1.5.2.dist-info/licenses/LICENSE
tests/__init__.py
tests/conftest.py
tests/test_backup.py
tests/test_cli.py
tests/test_restore.py
tests/test_restore_db_checks.py
tests/test_retention_policy.py
ctrl_z-1.5.2.dist-info/METADATA
ctrl_z-1.5.2.dist-info/WHEEL
ctrl_z-1.5.2.dist-info/top_level.txt
ctrl_z-1.5.2.dist-info/RECORD
