Metadata-Version: 2.4
Name: CTRL-Z
Version: 1.5.2
Summary: A Django backup and recovery tool
Home-page: https://github.com/isprojects/ctrl-z
Author: ISPnext B.V, Sergei Maertens
Author-email: support@ispnext.com
License: MIT
Keywords: django,backup,recovery
Classifier: Development Status :: 5 - Production/Stable
Classifier: Framework :: Django
Classifier: Framework :: Django :: 4.2
Classifier: Framework :: Django :: 5.2
Classifier: Intended Audience :: Developers
Classifier: Operating System :: Unix
Classifier: Operating System :: MacOS
Classifier: Operating System :: Microsoft :: Windows
Classifier: Programming Language :: Python :: 3.11
Classifier: Programming Language :: Python :: 3.12
Classifier: Programming Language :: Python :: 3.13
Classifier: Topic :: Software Development :: Libraries :: Python Modules
License-File: LICENSE
Requires-Dist: django
Requires-Dist: python-dateutil
Requires-Dist: pyyaml
Provides-Extra: tests
Requires-Dist: psycopg2-binary; extra == "tests"
Requires-Dist: pytest; extra == "tests"
Requires-Dist: pytest-django; extra == "tests"
Requires-Dist: freezegun; extra == "tests"
Requires-Dist: pytest-mock; extra == "tests"
Requires-Dist: tox; extra == "tests"
Requires-Dist: isort; extra == "tests"
Provides-Extra: pep8
Requires-Dist: flake8; extra == "pep8"
Provides-Extra: coverage
Requires-Dist: pytest-cov; extra == "coverage"
Provides-Extra: docs
Requires-Dist: sphinx; extra == "docs"
Requires-Dist: sphinx-rtd-theme; extra == "docs"
Provides-Extra: release
Requires-Dist: zest.releaser; extra == "release"
Dynamic: license-file
